{
  "document_id": "9c42879b11516db3",
  "document_type": "race_director_notes",
  "source_url": "https://www.fia.com/system/files/decision-document/2026_monaco_grand_prix_-_infringement_-_car_11_-_failing_to_follow_race_directors_event_notes_-_practice_starts.pdf",
  "parser_version": "fia-parser-v1",
  "parsed_at": "2026-06-08T21:20:32.920974+05:30",
  "confidence": 0.55,
  "classification": [],
  "upgrades": [],
  "pu_features": {},
  "infringements": {},
  "raw_text_excerpt": "2026 MONACO GRAND PRIX\n07 - 09 June 2026\nThe Stewards\nFrom The Stewards\nTo The Team Manager,\nCadillac Formula 1 Team\nDocument 86\nDate 07 June 2026\nTime 19:38\nThe Stewards, having received a report from the Race Director, have considered the following\nmatter and determine the following:\nNo / Driver 11 - Sergio Perez\nCompetitor Cadillac Formula 1 Team\nTime 14:20\nSession Reconnaissance Laps\nFact Car 11 failed to follow the Race Directors instructions regarding practice starts\nInfringement Breach of Article 12.2.1.i of the International Sporting Code and non-compliance with\nRace Director’s Event Note (item 13.6, document 48).\nDecision Driver: Reprimand (Driving).\nThis is the driver’s 1st reprimand of the season.\nReason The Stewards heard from the driver of Car 11 (Sergio Perez), team representative\nand reviewed positioning/marshalling system data, video and in-car video evidence.\nThe driver admitted that he had made a practice start in the wrong position.\nCompetitors are reminded that they have the right to appeal certain decisions of the\nStewards, in accordance with Article 15 of the FIA International Sporting Code and\nChapter 5 of the FIA Judicial and Disciplinary Rules, within the a"
}